[{"vid": "EfuSYmCQSY8", "cid": "UgyQTK4VTUtDztTtHgF4AaABAg", "comment": "Now I finally understand spontaneity", "votes": "0", "replies": "", "reply": false}, {"vid": "EfuSYmCQSY8", "cid": "UgzL3zTCL6ZJU2C4he14AaABAg", "comment": "isn't two level inversion impossible anyway?", "votes": "0", "replies": "1", "reply": false}, {"vid": "EfuSYmCQSY8", "cid": "UgycjDKawkzTJqDcVD94AaABAg", "comment": "First", "votes": "4", "replies": "", "reply": false}, {"vid": "EfuSYmCQSY8", "cid": "UgzL3zTCL6ZJU2C4he14AaABAg.9U85DO4K-Mp9w2vV0J2Lpt", "comment": "@GrahamSchmidt-ne3wx I honestly don't remember what part of the video I was responding to but can you elaborate?", "votes": "0", "replies": "", "reply": true}]