[{"vid": "ge09GjFUmKg", "cid": "UgwB98hCspFBzpziZy14AaABAg", "comment": "Sir plss complete the series", "votes": "0", "replies": "", "reply": false}, {"vid": "ge09GjFUmKg", "cid": "UgzRlhPD3doecI9LvsR4AaABAg", "comment": "Sir 15/15 is not giving proper answer in 4 bit what should I do", "votes": "0", "replies": "", "reply": false}, {"vid": "ge09GjFUmKg", "cid": "Ugy1goNzbJz7CVE44yF4AaABAg", "comment": "sir can u please complete this playlist..it will be a great help for us..", "votes": "2", "replies": "", "reply": false}, {"vid": "ge09GjFUmKg", "cid": "UgyD1VEChJHxPeI-l3d4AaABAg", "comment": "Please complete these playlist", "votes": "1", "replies": "", "reply": false}, {"vid": "ge09GjFUmKg", "cid": "UgyPDfOgcdGs5NSH2md4AaABAg", "comment": "How much faster is restoring division vs non-restoring division? Also, are the execution times fixed for the same size of dividend and divisor?", "votes": "2", "replies": "", "reply": false}, {"vid": "ge09GjFUmKg", "cid": "UgxK6Cdl9_3_gc7HgZZ4AaABAg", "comment": "please\uff01\uff01\uff01", "votes": "2", "replies": "1", "reply": false}, {"vid": "ge09GjFUmKg", "cid": "UgxR2YBAhD9XG48Q_kF4AaABAg", "comment": "From which video pipeline topics are discussed?", "votes": "3", "replies": "", "reply": false}, {"vid": "ge09GjFUmKg", "cid": "Ugxnhv9j-8YDDtyC4D54AaABAg", "comment": "sir please complete this playlist as exams are near , how many more lectures are left ?", "votes": "14", "replies": "", "reply": false}, {"vid": "ge09GjFUmKg", "cid": "Ugys7tpRVEzpELY2N_N4AaABAg", "comment": "Sir, Can you please upload new videos of DBMS?", "votes": "0", "replies": "", "reply": false}, {"vid": "ge09GjFUmKg", "cid": "UgxuPjOM4BDrXXsbc7N4AaABAg", "comment": "Hello sir completely python course please", "votes": "0", "replies": "", "reply": false}, {"vid": "ge09GjFUmKg", "cid": "Ugzr1Z8AAzwL--P4loF4AaABAg", "comment": "Please sir start sir", "votes": "0", "replies": "", "reply": false}, {"vid": "ge09GjFUmKg", "cid": "UgwkvYBtWcl0x2LPzxF4AaABAg", "comment": "It's my dream sir to learn microprocessor course", "votes": "0", "replies": "", "reply": false}, {"vid": "ge09GjFUmKg", "cid": "Ugxail04MPF-euZsC3Z4AaABAg", "comment": "Sir please make microprocessor course please sir", "votes": "0", "replies": "", "reply": false}, {"vid": "ge09GjFUmKg", "cid": "Ugz6NtJfbpogt06GZyd4AaABAg", "comment": "Please make videos asap on compiler design series and DBMS series. We are waiting for your videos. \ud83d\ude4f\ud83d\ude4f\u2764\ufe0f", "votes": "0", "replies": "", "reply": false}, {"vid": "ge09GjFUmKg", "cid": "UgyO48a7iKcPKBXiamN4AaABAg", "comment": "Sir we want complete python course", "votes": "0", "replies": "", "reply": false}, {"vid": "ge09GjFUmKg", "cid": "UgxK6Cdl9_3_gc7HgZZ4AaABAg.9r0_GuM-gqx9sxsE9ZB0as", "comment": "!!!", "votes": "2", "replies": "", "reply": true}]