[{"vid": "UwERCzJv-y8", "cid": "Ugypzc3xSobl8mRqO2x4AaABAg", "comment": "1 0110110 0 1101111 0 1110010  Even Parity is For this  1, 0, 0", "votes": "0", "replies": "", "reply": false}, {"vid": "UwERCzJv-y8", "cid": "UgyyzkJkKgTNkT9fVDp4AaABAg", "comment": "1 1110110 0 1101111 0 1110010 is that correct ?", "votes": "2", "replies": "1", "reply": false}, {"vid": "UwERCzJv-y8", "cid": "Ugx4ybdYo2f4772knr94AaABAg", "comment": "Sir, Thank You So Much for This Amazing Lecture \ud83d\ude0a\r Lecture - 45 Completed \u2714", "votes": "6", "replies": "", "reply": false}, {"vid": "UwERCzJv-y8", "cid": "UgzTSFNVSDlGS3P9QUl4AaABAg", "comment": "Sir , can you please post RDBMS vdos", "votes": "0", "replies": "", "reply": false}, {"vid": "UwERCzJv-y8", "cid": "UgxvOKGNxBZfLVCtTqJ4AaABAg", "comment": "thank you", "votes": "0", "replies": "", "reply": false}, {"vid": "UwERCzJv-y8", "cid": "UgyKtDxRg_wrGIU88wd4AaABAg", "comment": "the given three blocks of homework have no transmission errors all blocks having even number of 1's after solving. is it correct..?", "votes": "0", "replies": "1", "reply": false}, {"vid": "UwERCzJv-y8", "cid": "Ugzv8AR0LJ4A9lgQpYl4AaABAg", "comment": "1|1110110      0|1101111    0|1110010", "votes": "3", "replies": "", "reply": false}, {"vid": "UwERCzJv-y8", "cid": "Ugxnyd418WuWY07Rj5x4AaABAg", "comment": "What if the parity bit is changed, but the message is still the same?", "votes": "1", "replies": "", "reply": false}, {"vid": "UwERCzJv-y8", "cid": "UgybpRMeGKFUL5obn_t4AaABAg", "comment": "1110110 append with 0; 1101111 append with 1; 1110010 append with 1;", "votes": "0", "replies": "", "reply": false}, {"vid": "UwERCzJv-y8", "cid": "UgzJcaPC7HLG7Cu5_Cd4AaABAg", "comment": "you said that VRC can detect burst errors only if the number of ones is odd.but in the ppt  is given that VRC can detect errors if the number of errors is odd.", "votes": "5", "replies": "", "reply": false}, {"vid": "UwERCzJv-y8", "cid": "UgyKqrylWJJCGicPNMJ4AaABAg", "comment": "thanks sir \ud83d\ude0a\ud83d\ude0a", "votes": "0", "replies": "", "reply": false}, {"vid": "UwERCzJv-y8", "cid": "UgxzfQ96itU0k_zmEVp4AaABAg", "comment": "Thanks for making our learning so easy!!\ud83d\ude0d\ud83d\ude0d", "votes": "0", "replies": "", "reply": false}, {"vid": "UwERCzJv-y8", "cid": "UgxEhTUm3rcZADZN1xJ4AaABAg", "comment": "1110110 = Append 1 in front of the first block to get even 1s at the receiver, 1101111 = The number of 1s in the second block is already even(6); so u just append 0 in front to maintain even parity. 1110010 =  Since the number of 1s is even (4), append 0 in front in the 3rd block to maintain even parity", "votes": "0", "replies": "", "reply": false}, {"vid": "UwERCzJv-y8", "cid": "UgwCZvHb1tjmR8hZtUh4AaABAg", "comment": "Nice explanation.", "votes": "1", "replies": "", "reply": false}, {"vid": "UwERCzJv-y8", "cid": "UgwDaaVetY7LYaS_s-h4AaABAg", "comment": "11110110 1101111 1110010", "votes": "0", "replies": "", "reply": false}, {"vid": "UwERCzJv-y8", "cid": "UgzS02kRt7Tv8I1P-BB4AaABAg", "comment": "thank you very much man , very usefull good job", "votes": "1", "replies": "", "reply": false}, {"vid": "UwERCzJv-y8", "cid": "UgxrPOz0RsusWZ083ml4AaABAg", "comment": "Do we add 1 or 0 at the start or at the end? For example the data se 0001, is 10001 is correct or 00011? Because in my course the parity bit is added at the end", "votes": "5", "replies": "1", "reply": false}, {"vid": "UwERCzJv-y8", "cid": "UgyyMcHTeJenEAMBCnR4AaABAg", "comment": "Thnak you so much\u263a", "votes": "0", "replies": "", "reply": false}, {"vid": "UwERCzJv-y8", "cid": "UgxC_emPfMzUgxolCGR4AaABAg", "comment": "Excellent presentation", "votes": "1", "replies": "", "reply": false}, {"vid": "UwERCzJv-y8", "cid": "UgwgGSk7H4D22rkKbX54AaABAg", "comment": "11110110 01101111 01110010", "votes": "0", "replies": "", "reply": false}, {"vid": "UwERCzJv-y8", "cid": "UgyyzkJkKgTNkT9fVDp4AaABAg.A2Ak2snBrmgA5jnexZbZF_", "comment": "yess", "votes": "0", "replies": "", "reply": true}, {"vid": "UwERCzJv-y8", "cid": "UgyKtDxRg_wrGIU88wd4AaABAg.9m4GKHPZHwU9qKYa0mh22Q", "comment": "no sir, the first one have odd number of 1's", "votes": "0", "replies": "", "reply": true}, {"vid": "UwERCzJv-y8", "cid": "UgxrPOz0RsusWZ083ml4AaABAg.9YLw1ThbOnS9kCbmgQACmN", "comment": "10001 is correct, add on the left side(i.e as a most significant bit)", "votes": "2", "replies": "", "reply": true}, {"vid": "UwERCzJv-y8", "cid": "UgzUalnsupeV4qZRRTF4AaABAg", "comment": "thank you\ud83d\udc9c does it matter where I place the parity bit?", "votes": "0", "replies": "1", "reply": false}, {"vid": "UwERCzJv-y8", "cid": "Ugzm_Nv7BtRaF8QX-3p4AaABAg", "comment": "8/7/21 01:04 am", "votes": "0", "replies": "", "reply": false}, {"vid": "UwERCzJv-y8", "cid": "UgyYgPcI1sbnN-QgWrx4AaABAg", "comment": "1 0 0", "votes": "2", "replies": "", "reply": false}, {"vid": "UwERCzJv-y8", "cid": "Ugw41ydx0YPzsRzCFxJ4AaABAg", "comment": "What if data more than 8 and 8 bit", "votes": "0", "replies": "1", "reply": false}, {"vid": "UwERCzJv-y8", "cid": "Ugw11a-Vmo-vmPoDd-l4AaABAg", "comment": "It's 100", "votes": "0", "replies": "", "reply": false}, {"vid": "UwERCzJv-y8", "cid": "UgzWaZZsawFPTNbakuB4AaABAg", "comment": "1 0 0", "votes": "1", "replies": "", "reply": false}, {"vid": "UwERCzJv-y8", "cid": "UgxLvJ48LPYKwBbenrp4AaABAg", "comment": "1 00", "votes": "1", "replies": "", "reply": false}, {"vid": "UwERCzJv-y8", "cid": "UgwlG22UEivoNOrfbwp4AaABAg", "comment": "Very well understandable\ud83d\udc4c\ud83c\udffb", "votes": "11", "replies": "", "reply": false}, {"vid": "UwERCzJv-y8", "cid": "UgwLYtr-0uvffmh4QM14AaABAg", "comment": "Really good\ud83d\udd25", "votes": "5", "replies": "", "reply": false}, {"vid": "UwERCzJv-y8", "cid": "UgwY_0A6CzyJlOf8OAl4AaABAg", "comment": "Thank you", "votes": "0", "replies": "", "reply": false}, {"vid": "UwERCzJv-y8", "cid": "UgxuWyeVppcV3Ed33WN4AaABAg", "comment": "What if the data itself have odd number of ones..whether it add 1 to make it even", "votes": "2", "replies": "2", "reply": false}, {"vid": "UwERCzJv-y8", "cid": "UgzQBcygpdyNooit0S94AaABAg", "comment": "Guys if this was bit confusing let me put it short here, In this case receiver accepts data with  even number of 1's. When there are odd number of 1's in sender then, parity checker will append 1 to the data to make the count of 1's even so that receiver could accept. If there were any transmission errors due to which the count of 1's becomes odd then receiver will reject. . . . After reading this watch the lecture again to understand better \u270c\ufe0f", "votes": "41", "replies": "2", "reply": false}, {"vid": "UwERCzJv-y8", "cid": "UgzsC-q-8u770-D0NaJ4AaABAg", "comment": "I m a recent viewer....very useful \ud83d\udc9d\ud83d\udc9d", "votes": "3", "replies": "", "reply": false}, {"vid": "UwERCzJv-y8", "cid": "Ugy7on9sPZ6Zy_9jrYp4AaABAg", "comment": "1 0 0", "votes": "3", "replies": "", "reply": false}, {"vid": "UwERCzJv-y8", "cid": "Ugwu8TpqjJN9Y8lLixB4AaABAg", "comment": "what if the parity bit gets corrupted?", "votes": "2", "replies": "", "reply": false}, {"vid": "UwERCzJv-y8", "cid": "UgzMZ2PiMjOr3bwxSn94AaABAg", "comment": "clean explanation....", "votes": "0", "replies": "", "reply": false}, {"vid": "UwERCzJv-y8", "cid": "Ugw8vmbBbJmy6UjRRcN4AaABAg", "comment": "This is called quality\ud83d\ude43\ud83d\udc12", "votes": "54", "replies": "", "reply": false}, {"vid": "UwERCzJv-y8", "cid": "UgzSLMzUtAVnI3ruiLh4AaABAg", "comment": "0 1 0", "votes": "0", "replies": "", "reply": false}, {"vid": "UwERCzJv-y8", "cid": "UgzazSUNqZRwhPTEePN4AaABAg", "comment": "11110110  01101111  01110010", "votes": "0", "replies": "", "reply": false}, {"vid": "UwERCzJv-y8", "cid": "Ugxo16MzdgeGEoRbimB4AaABAg", "comment": "Thanks for making our learning so easy!!\ud83d\ude0d\ud83d\ude0d", "votes": "17", "replies": "", "reply": false}, {"vid": "UwERCzJv-y8", "cid": "UgzUalnsupeV4qZRRTF4AaABAg.9Qcx7enCNJf9oeT7-a2db5", "comment": "yeah", "votes": "0", "replies": "", "reply": true}, {"vid": "UwERCzJv-y8", "cid": "Ugw41ydx0YPzsRzCFxJ4AaABAg.9LojIGiT8Du9Rh-jakyMII", "comment": "u can use even parity check or odd parity check anytym", "votes": "0", "replies": "", "reply": true}, {"vid": "UwERCzJv-y8", "cid": "UgxuWyeVppcV3Ed33WN4AaABAg.9HofGFwlloH9YRBoYF-v8s", "comment": "then parity is 1..if u using even parity generator", "votes": "0", "replies": "", "reply": true}, {"vid": "UwERCzJv-y8", "cid": "UgxuWyeVppcV3Ed33WN4AaABAg.9HofGFwlloH9blBtluYkC7", "comment": "\u00a0@rakshitpandey7517\u00a0 will you just share the answers ... please", "votes": "0", "replies": "", "reply": true}, {"vid": "UwERCzJv-y8", "cid": "UgzQBcygpdyNooit0S94AaABAg.9HH6fUOteF19P00mUo_t1D", "comment": "Ok , suppose the sender send even number of one and due to transmission errorr it become odd When reciver checks the number of 1 it found it odd then it check the parity bait if it is one it will accept it.", "votes": "1", "replies": "", "reply": true}, {"vid": "UwERCzJv-y8", "cid": "UgzQBcygpdyNooit0S94AaABAg.9HH6fUOteF19UI28kOqf02", "comment": "\u00a0@half_notes_9133\u00a0 nope it won't", "votes": "0", "replies": "", "reply": true}, {"vid": "UwERCzJv-y8", "cid": "UgxSxbohGgc98a5S-Bd4AaABAg", "comment": "1 0 0", "votes": "2", "replies": "", "reply": false}, {"vid": "UwERCzJv-y8", "cid": "UgwduSVpgPHbKlVB2dl4AaABAg", "comment": "2:30", "votes": "2", "replies": "1", "reply": false}, {"vid": "UwERCzJv-y8", "cid": "Ugy8KLGsGDzJTtynYKB4AaABAg", "comment": "1110110 = Append 1 in front of the first block to get even 1s at the receiver, 1101111 = The number of 1s in the second block is already even(6); so u just append 0 in front to maintain even parity. 1110010 =  Since the number of 1s is even (4), append 0 in front in the 3rd block to maintain even parity", "votes": "264", "replies": "10", "reply": false}, {"vid": "UwERCzJv-y8", "cid": "UgxbQKYR7W1DK2S2Lkp4AaABAg", "comment": "Can we also use Odd Parity Generator in VRC?", "votes": "4", "replies": "2", "reply": false}, {"vid": "UwERCzJv-y8", "cid": "UgzukxRoi5XYkwQMCxp4AaABAg", "comment": "Wrong explanation!!!! At 3:00", "votes": "0", "replies": "1", "reply": false}, {"vid": "UwERCzJv-y8", "cid": "UgwxPHUgY9lL8DfjZP94AaABAg", "comment": "Thanks sir,!!.. 1 0 0  Parity can be odd or even right?.  .", "votes": "4", "replies": "1", "reply": false}, {"vid": "UwERCzJv-y8", "cid": "Ugx4SpG8bCjKFBn-s5F4AaABAg", "comment": "1 0 0", "votes": "5", "replies": "", "reply": false}, {"vid": "UwERCzJv-y8", "cid": "Ugz-bqhLHy7b1rQsXLB4AaABAg", "comment": "thank you sir....pls give us more  videos....", "votes": "0", "replies": "", "reply": false}, {"vid": "UwERCzJv-y8", "cid": "UgyzgK3mLwz6bniUDgB4AaABAg", "comment": "Thank you sir and please post all error detection methods also", "votes": "1", "replies": "", "reply": false}, {"vid": "UwERCzJv-y8", "cid": "Ugxs8pzVae9M78B8sdd4AaABAg", "comment": "Hey Nice lecture  Btw which book are you following for this course?", "votes": "8", "replies": "", "reply": false}, {"vid": "UwERCzJv-y8", "cid": "UgwduSVpgPHbKlVB2dl4AaABAg.99fCVMKajPK9AzU0_QbhA1", "comment": "What happened at 2:30 ?", "votes": "1", "replies": "", "reply": true}, {"vid": "UwERCzJv-y8", "cid": "Ugy8KLGsGDzJTtynYKB4AaABAg.99Xd21CfG9U9LsVChX1ztx", "comment": "Thankyou so much for the explanation I was confused and didn't know what to to do", "votes": "14", "replies": "", "reply": true}, {"vid": "UwERCzJv-y8", "cid": "Ugy8KLGsGDzJTtynYKB4AaABAg.99Xd21CfG9U9R37Y5e3YKL", "comment": "Excellent explanation sir", "votes": "5", "replies": "", "reply": true}, {"vid": "UwERCzJv-y8", "cid": "Ugy8KLGsGDzJTtynYKB4AaABAg.99Xd21CfG9U9bXC_byVEMb", "comment": "Thanks for explanation \ud83d\ude4f\ud83d\ude4f", "votes": "2", "replies": "", "reply": true}, {"vid": "UwERCzJv-y8", "cid": "Ugy8KLGsGDzJTtynYKB4AaABAg.99Xd21CfG9U9cJL-Q1e4pS", "comment": "1110110, 1 = 5(one) +1(one) = 6 even no error, 1101111, 0 = 6(one) already even so add 0 no error, 111001, 0 = 4(one) even so add 0 no error", "votes": "0", "replies": "", "reply": true}, {"vid": "UwERCzJv-y8", "cid": "Ugy8KLGsGDzJTtynYKB4AaABAg.99Xd21CfG9U9ei6adO6L7I", "comment": "thanks bro\ud83d\ude0d", "votes": "2", "replies": "", "reply": true}, {"vid": "UwERCzJv-y8", "cid": "Ugy8KLGsGDzJTtynYKB4AaABAg.99Xd21CfG9U9htjEuA5SyU", "comment": "Right", "votes": "1", "replies": "", "reply": true}, {"vid": "UwERCzJv-y8", "cid": "Ugy8KLGsGDzJTtynYKB4AaABAg.99Xd21CfG9U9lcagyH5fye", "comment": "In this our main target  The give word should be even aa ? Can u clarify me", "votes": "1", "replies": "", "reply": true}, {"vid": "UwERCzJv-y8", "cid": "Ugy8KLGsGDzJTtynYKB4AaABAg.99Xd21CfG9U9oeTF0MsbXk", "comment": "\u00a0@509nandini7\u00a0 fr even parity yes na", "votes": "0", "replies": "", "reply": true}, {"vid": "UwERCzJv-y8", "cid": "Ugy8KLGsGDzJTtynYKB4AaABAg.99Xd21CfG9U9q2xb3QA5lC", "comment": "See 2:57  I think you are wrong for writing data to reciever side it will be a) 11110110 B)01101111 C)01110010", "votes": "10", "replies": "", "reply": true}, {"vid": "UwERCzJv-y8", "cid": "Ugy8KLGsGDzJTtynYKB4AaABAg.99Xd21CfG9U9wxgClJnpsc", "comment": "I don't understand properly \ud83d\ude22", "votes": "3", "replies": "", "reply": true}, {"vid": "UwERCzJv-y8", "cid": "UgxbQKYR7W1DK2S2Lkp4AaABAg.98zZhGbkT-O9ArGMqzvoFN", "comment": "Yes We can", "votes": "0", "replies": "", "reply": true}, {"vid": "UwERCzJv-y8", "cid": "UgxbQKYR7W1DK2S2Lkp4AaABAg.98zZhGbkT-O9Gnjb1B3Swt", "comment": "Yess", "votes": "0", "replies": "", "reply": true}, {"vid": "UwERCzJv-y8", "cid": "UgzukxRoi5XYkwQMCxp4AaABAg.97OE4cLfkI-97nJLgD8cO3", "comment": "What's wrong there??", "votes": "2", "replies": "", "reply": true}, {"vid": "UwERCzJv-y8", "cid": "UgwxPHUgY9lL8DfjZP94AaABAg.96vJKGQbO1R99XdGxBPN90", "comment": "The determinant for even parity is the number of 1s which must be even (2,4,6,8............)", "votes": "0", "replies": "", "reply": true}]