[{"vid": "xFliq3EFN6I", "cid": "Ugw7U5Ff0g8qHQwcJjR4AaABAg", "comment": "C", "votes": "0", "replies": "", "reply": false}, {"vid": "xFliq3EFN6I", "cid": "Ugzfp6aitEh-XvuhRNh4AaABAg", "comment": "Answer is C", "votes": "0", "replies": "", "reply": false}, {"vid": "xFliq3EFN6I", "cid": "UgzJPub2e7nn0RN35mZ4AaABAg", "comment": "option c", "votes": "0", "replies": "", "reply": false}, {"vid": "xFliq3EFN6I", "cid": "UgzKW5CfVpK0sWrhyMR4AaABAg", "comment": "answer is C", "votes": "1", "replies": "", "reply": false}, {"vid": "xFliq3EFN6I", "cid": "UgwkaBleXlGqRD7SJBN4AaABAg", "comment": "Answer is C", "votes": "0", "replies": "", "reply": false}, {"vid": "xFliq3EFN6I", "cid": "UgyPdveW1JFeb3cRcdJ4AaABAg", "comment": "option c", "votes": "0", "replies": "", "reply": false}, {"vid": "xFliq3EFN6I", "cid": "UgwnO38y_f-P8RRUuDN4AaABAg", "comment": "16 bit port 48 bit MAC address ipV4 32 bits ipV6 128bits", "votes": "0", "replies": "", "reply": false}, {"vid": "xFliq3EFN6I", "cid": "Ugy-GChDlVb8QIp0sRd4AaABAg", "comment": "c", "votes": "0", "replies": "", "reply": false}, {"vid": "xFliq3EFN6I", "cid": "Ugx9S3zM5DXG38P_C7p4AaABAg", "comment": "Ans c", "votes": "0", "replies": "", "reply": false}, {"vid": "xFliq3EFN6I", "cid": "UgzDgEgALdljLiM8P1t4AaABAg", "comment": "C", "votes": "0", "replies": "", "reply": false}, {"vid": "xFliq3EFN6I", "cid": "UgwIYdM6a0Jn4IhkkEh4AaABAg", "comment": "the answer is c because the maximum number of the port address is 65535 if you  converted to binary it will be 1111111111111111 mean 16 bit , the port adderss lesson is number 10 in the lecture", "votes": "21", "replies": "", "reply": false}, {"vid": "xFliq3EFN6I", "cid": "UgyjnNxagIdPHvCl7St4AaABAg", "comment": "c is correct answer .... Google it to check  \ud83d\ude42\ud83d\ude01", "votes": "0", "replies": "", "reply": false}, {"vid": "xFliq3EFN6I", "cid": "UgxYFV9aAsmDdLrIuQh4AaABAg", "comment": "C", "votes": "0", "replies": "", "reply": false}, {"vid": "xFliq3EFN6I", "cid": "UgzYi_RHpmJY-NDKYTx4AaABAg", "comment": "Is D Correct ?", "votes": "0", "replies": "1", "reply": false}, {"vid": "xFliq3EFN6I", "cid": "Ugw-B0eLWaXoR9FMTAJ4AaABAg", "comment": "D MAC address min length 46", "votes": "1", "replies": "", "reply": false}, {"vid": "xFliq3EFN6I", "cid": "Ugwz6ML3NQkbkG2YdLJ4AaABAg", "comment": "how to find out what is port address", "votes": "0", "replies": "", "reply": false}, {"vid": "xFliq3EFN6I", "cid": "UgwuhAd-LWL3cWKHi7t4AaABAg", "comment": "this man seems like dora exploring cs", "votes": "10", "replies": "", "reply": false}, {"vid": "xFliq3EFN6I", "cid": "UgwmRTtDiAdyD6A6jOV4AaABAg", "comment": "Answer is c", "votes": "0", "replies": "", "reply": false}, {"vid": "xFliq3EFN6I", "cid": "UgzrHj7Z8kMd8zQS9Sh4AaABAg", "comment": "Option C.", "votes": "1", "replies": "", "reply": false}, {"vid": "xFliq3EFN6I", "cid": "Ugz7mqsXhCAC8dA0bet4AaABAg", "comment": "C", "votes": "1", "replies": "", "reply": false}, {"vid": "xFliq3EFN6I", "cid": "UgzYi_RHpmJY-NDKYTx4AaABAg.9Ojt78BsV1z9Osmc8WqIIl", "comment": "No mac is of 48 bits", "votes": "0", "replies": "", "reply": true}, {"vid": "xFliq3EFN6I", "cid": "Ugx17QUnRi5QIFHOunp4AaABAg", "comment": "Option D is correct ??", "votes": "3", "replies": "1", "reply": false}, {"vid": "xFliq3EFN6I", "cid": "UgxvInCViGKM-g2eMix4AaABAg", "comment": "C", "votes": "0", "replies": "", "reply": false}, {"vid": "xFliq3EFN6I", "cid": "UgxOnvxzuK8yFHA8jpx4AaABAg", "comment": "Most of the people answered option C .how???", "votes": "0", "replies": "2", "reply": false}, {"vid": "xFliq3EFN6I", "cid": "Ugy_vms0pWt6TcrSpNx4AaABAg", "comment": "c", "votes": "0", "replies": "", "reply": false}, {"vid": "xFliq3EFN6I", "cid": "UgwzVsqIP2RqRSnD_MJ4AaABAg", "comment": "C", "votes": "0", "replies": "", "reply": false}, {"vid": "xFliq3EFN6I", "cid": "UgzsKSJq8o9alOz2MqZ4AaABAg", "comment": "C", "votes": "0", "replies": "", "reply": false}, {"vid": "xFliq3EFN6I", "cid": "Ugz3k8TUB7hcO5VpU-B4AaABAg", "comment": "Option \" C\"", "votes": "1", "replies": "", "reply": false}, {"vid": "xFliq3EFN6I", "cid": "UgzJop_Kh43-QvOIqup4AaABAg", "comment": "7:17 1mbps=10^6 bits/sec then 10mbps=10^7 bits/sec", "votes": "1", "replies": "1", "reply": false}, {"vid": "xFliq3EFN6I", "cid": "Ugz8zLERjoKhhCl49vR4AaABAg", "comment": "1 mb=1024 kb,,,,why u multiplied 1000", "votes": "5", "replies": "4", "reply": false}, {"vid": "xFliq3EFN6I", "cid": "Ugydarphr3yto1DoR214AaABAg", "comment": "c", "votes": "0", "replies": "", "reply": false}, {"vid": "xFliq3EFN6I", "cid": "UgxScHatZtVxdeomYQB4AaABAg", "comment": "Answer is C.. Sir Plz upload videos regularly.. And thanks Neso Academy.. \ud83d\ude03", "votes": "9", "replies": "", "reply": false}, {"vid": "xFliq3EFN6I", "cid": "UgyqlEBV8MeM8tN6wtZ4AaABAg", "comment": "Plz complete the course early", "votes": "3", "replies": "", "reply": false}, {"vid": "xFliq3EFN6I", "cid": "UgxRukzZmJvuxmSvHk14AaABAg", "comment": "the answer is C", "votes": "1", "replies": "", "reply": false}, {"vid": "xFliq3EFN6I", "cid": "UgxDPkMpT2HLA_v-gDR4AaABAg", "comment": "Sir Please upload Videos Daily.", "votes": "1", "replies": "", "reply": false}, {"vid": "xFliq3EFN6I", "cid": "Ugx17QUnRi5QIFHOunp4AaABAg.9HCXHcPM9hi9PEm86Kh1P_", "comment": "MAc address is 48 bit so c is correct google it", "votes": "0", "replies": "", "reply": true}, {"vid": "xFliq3EFN6I", "cid": "UgxOnvxzuK8yFHA8jpx4AaABAg.9GEHIxxdVwh9IUvlyaRh7t", "comment": "Port Address is of 16 bits.", "votes": "0", "replies": "", "reply": true}, {"vid": "xFliq3EFN6I", "cid": "UgxOnvxzuK8yFHA8jpx4AaABAg.9GEHIxxdVwh9OIkPhhcQzP", "comment": "both destination and source mac address have 6 bytes(48 bits)not 46.46 is minimum payload length", "votes": "0", "replies": "", "reply": true}, {"vid": "xFliq3EFN6I", "cid": "UgzJop_Kh43-QvOIqup4AaABAg.99liSRTFQPH9G7VJWrlVTV", "comment": "the final answer is 51.2 microsecs", "votes": "3", "replies": "", "reply": true}, {"vid": "xFliq3EFN6I", "cid": "Ugz8zLERjoKhhCl49vR4AaABAg.99liJASqToH9G7VSYUNzw4", "comment": "1 mb = 1024 kb ( base 2),  while 1mb = 1000kb ( in base 10)", "votes": "0", "replies": "", "reply": true}, {"vid": "xFliq3EFN6I", "cid": "Ugz8zLERjoKhhCl49vR4AaABAg.99liJASqToH9NEK-OsWQhl", "comment": "Here we are not converting bytes to bits", "votes": "0", "replies": "", "reply": true}, {"vid": "xFliq3EFN6I", "cid": "Ugz8zLERjoKhhCl49vR4AaABAg.99liJASqToH9NGzhNAyk7H", "comment": "Here we converting Mbps into bps so we multiply it into 10 ^6", "votes": "2", "replies": "", "reply": true}, {"vid": "xFliq3EFN6I", "cid": "Ugz8zLERjoKhhCl49vR4AaABAg.99liJASqToH9NWFLO0NQ7e", "comment": "\u00a0@skgeddha3207\u00a0 yeah but we have to convert into bits", "votes": "0", "replies": "", "reply": true}]